{
  "mon": {
    "Col LG01": {
      "9": 32,
      "10": 32,
      "11": 32,
      "12": 32,
      "13": 32,
      "14": 32,
      "15": 895,
      "16": 895
    },
    "Col LG02": {
      "9": 32,
      "10": 32,
      "11": 32,
      "12": 32,
      "13": 32,
      "14": 32,
      "16": 895,
      "18": 847,
      "19": 847,
      "20": 1
    },
    "Gold G01": {
      "9": 32,
      "10": 32,
      "11": 32,
      "12": 32,
      "13": 32,
      "14": 32,
      "15": 895,
      "16": 895,
      "18": 863,
      "19": 863,
      "20": 863
    },
    "Gold G02": {
      "9": 32,
      "10": 32,
      "11": 895,
      "12": 895,
      "13": 895,
      "14": 32,
      "15": 1022,
      "16": 1022
    },
    "Gold G03": {
      "9": 1023,
      "10": 1023,
      "11": 1023,
      "14": 863,
      "15": 863
    },
    "Gold G04": {
      "9": 2,
      "10": 2,
      "11": 2,
      "12": 2,
      "13": 2,
      "14": 2,
      "15": 2,
      "16": 2
    },
    "Gold G05": {
      "9": 32,
      "10": 895,
      "11": 895,
      "12": 895,
      "13": 895,
      "14": 895
    },
    "Gold G06": {
      "9": 32,
      "10": 32,
      "11": 32,
      "12": 32,
      "13": 895,
      "14": 895,
      "15": 1022,
      "16": 1022
    },
    "Gold G07": {
      "9": 32,
      "10": 32,
      "11": 32,
      "12": 895,
      "13": 895,
      "14": 32,
      "15": 863
    },
    "Gold G09": {
      "9": 32,
      "10": 895,
      "11": 895,
      "12": 895,
      "13": 32,
      "14": 39,
      "15": 7,
      "16": 7,
      "18": 4,
      "19": 4,
      "20": 4
    },
    "BUS 107": {
      "12": 863,
      "13": 863,
      "14": 863,
      "15": 1022,
      "16": 1022,
      "18": 991
    },
    "BUS 114": {
      "12": 862,
      "13": 862,
      "14": 862,
      "15": 1022,
      "16": 1022
    },
    "BUS 118": {
      "9": 351,
      "10": 351,
      "15": 862,
      "16": 862,
      "17": 862
    },
    "BUS 207": {
      "13": 862,
      "14": 862,
      "15": 862,
      "16": 862
    },
    "BUS 215": {
      "12": 863,
      "13": 863,
      "14": 863,
      "15": 863,
      "16": 863,
      "17": 863
    },
    "BUS 219": {
      "12": 863,
      "13": 863,
      "14": 63,
      "15": 1022,
      "16": 1022,
      "17": 863,
      "18": 863
    },
    "Quad 1001": {
      "9": 1023,
      "10": 1023,
      "11": 1023,
      "12": 894,
      "13": 894,
      "14": 512,
      "15": 514,
      "16": 2
    },
    "Quad 1042": {
      "10": 863,
      "11": 863,
      "12": 863,
      "13": 863,
      "14": 863
    },
    "Quad 1043": {
      "10": 519,
      "11": 519,
      "12": 519,
      "13": 512,
      "14": 895,
      "15": 895,
      "16": 895,
      "18": 895,
      "19": 895,
      "20": 895
    },
    "Quad 1045": {
      "10": 863,
      "11": 863,
      "12": 863,
      "13": 863,
      "14": 863
    },
    "Quad 1046": {
      "10": 863,
      "11": 863,
      "12": 863,
      "13": 863,
      "14": 863
    },
    "Quad 1047": {
      "10": 863,
      "11": 863,
      "12": 863,
      "13": 863,
      "14": 863,
      "15": 1020,
      "16": 1020
    },
    "Quad 1048": {
      "10": 863,
      "11": 863,
      "12": 863,
      "13": 863,
      "14": 863,
      "15": 863,
      "16": 863
    },
    "Quad 1049": {
      "16": 1023,
      "17": 1023
    },
    "Quad G025": {
      "11": 1023,
      "12": 1023,
      "15": 1022,
      "16": 1022
    },
    "Quad G026": {
      "9": 4,
      "10": 4,
      "11": 5,
      "12": 4,
      "13": 863,
      "14": 863,
      "16": 478,
      "17": 478
    },
    "Quad G027": {
      "10": 863,
      "11": 863
    },
    "Quad G031": {},
    "Quad G032": {},
    "Quad G033": {
      "8": 12,
      "9": 13,
      "10": 13,
      "11": 15,
      "12": 13,
      "13": 13,
      "14": 13,
      "15": 13,
      "16": 13,
      "17": 13,
      "18": 13
    },
    "Quad G034": {
      "13": 863,
      "14": 863,
      "15": 863,
      "16": 863,
      "18": 846,
      "19": 846
    },
    "Quad G040": {
      "13": 862,
      "14": 862,
      "15": 895,
      "16": 895,
      "18": 1020,
      "19": 1020,
      "20": 1020
    },
    "Quad G042": {
      "10": 863,
      "11": 863,
      "12": 863,
      "13": 863,
      "14": 863
    },
    "Quad G044": {
      "15": 863,
      "16": 863
    },
    "Quad G045": {
      "15": 863,
      "16": 863
    },
    "Quad G046": {
      "10": 863,
      "11": 863,
      "12": 863,
      "13": 863,
      "14": 863
    },
    "Quad G047": {
      "10": 863,
      "11": 863,
      "12": 863,
      "13": 863,
      "14": 863,
      "15": 1022,
      "16": 1022
    },
    "Quad G048": {
      "11": 4,
      "12": 4,
      "13": 4,
      "14": 4,
      "15": 4,
      "16": 4,
      "17": 5,
      "18": 5,
      "19": 4,
      "20": 4
    },
    "Quad G052": {
      "10": 863,
      "11": 863,
      "12": 863,
      "13": 863,
      "14": 863
    },
    "Quad G053": {
      "9": 863,
      "10": 863,
      "11": 863,
      "12": 863,
      "13": 863,
      "14": 863,
      "15": 863,
      "16": 863,
      "18": 4,
      "19": 4,
      "20": 4
    },
    "Quad G054": {
      "10": 863,
      "11": 863,
      "12": 863,
      "13": 863,
      "14": 863
    },
    "Quad G055": {
      "7": 1023,
      "8": 1023,
      "9": 1023,
      "10": 1023,
      "11": 1023,
      "12": 1023,
      "13": 1023,
      "14": 1023,
      "15": 1023,
      "16": 1023,
      "17": 1023,
      "18": 1023,
      "19": 1023,
      "20": 1023,
      "21": 1023
    },
    "Webst 250": {
      "9": 863,
      "15": 895,
      "16": 895
    },
    "Webst 251": {
      "9": 863,
      "10": 863,
      "11": 863,
      "12": 863,
      "13": 863,
      "14": 863,
      "16": 863,
      "17": 863
    },
    "Webst 252": {},
    "Webst 256": {
      "9": 63,
      "14": 1022,
      "15": 1022,
      "16": 1022
    },
    "Webst 302": {
      "13": 863,
      "14": 863,
      "15": 1022,
      "16": 1022
    },
    "RedC 2035": {
      "15": 1020,
      "16": 1020,
      "17": 1020
    },
    "RedC 3037": {
      "10": 991,
      "11": 991,
      "12": 991,
      "13": 991,
      "14": 991,
      "15": 1020,
      "16": 1020,
      "17": 1020
    },
    "RedC 4034": {
      "14": 863,
      "15": 863
    },
    "RedC M010": {
      "15": 895,
      "16": 895
    }
  },
  "tue": {
    "Col LG01": {
      "9": 32,
      "10": 32,
      "11": 32,
      "12": 32,
      "13": 1023,
      "14": 1023,
      "15": 991,
      "16": 991,
      "17": 991,
      "19": 1022,
      "20": 1022
    },
    "Col LG02": {
      "10": 1023,
      "11": 1023,
      "12": 1023,
      "13": 2,
      "14": 2,
      "15": 2,
      "18": 926,
      "19": 926
    },
    "Gold G01": {
      "9": 33,
      "10": 33,
      "11": 33,
      "12": 32,
      "13": 1023,
      "14": 1023,
      "17": 2,
      "18": 2,
      "19": 2
    },
    "Gold G02": {
      "9": 160,
      "10": 160,
      "11": 160,
      "12": 1023,
      "13": 1023,
      "14": 1023,
      "17": 2,
      "18": 2,
      "19": 2
    },
    "Gold G03": {
      "9": 32,
      "10": 32,
      "11": 32,
      "12": 1023,
      "13": 1023,
      "14": 1023,
      "15": 991,
      "16": 991,
      "17": 991
    },
    "Gold G04": {
      "9": 1023,
      "10": 1023,
      "11": 1023
    },
    "Gold G05": {
      "9": 32,
      "10": 32,
      "11": 32,
      "12": 32,
      "13": 32,
      "14": 32
    },
    "Gold G06": {
      "9": 32,
      "10": 511,
      "11": 511,
      "12": 32,
      "13": 32,
      "14": 32,
      "15": 479,
      "16": 479
    },
    "Gold G07": {
      "9": 32,
      "10": 32,
      "11": 1023,
      "12": 1023,
      "13": 1023,
      "14": 1023,
      "15": 991,
      "18": 1022,
      "19": 1022
    },
    "Gold G09": {
      "9": 32,
      "10": 1023,
      "11": 1023,
      "12": 32,
      "13": 32,
      "14": 32,
      "15": 991,
      "16": 991,
      "17": 255,
      "18": 255,
      "19": 255
    },
    "BUS 107": {
      "9": 991,
      "10": 991,
      "11": 991,
      "12": 1023,
      "13": 1023,
      "14": 991,
      "15": 991,
      "16": 991,
      "18": 991
    },
    "BUS 114": {
      "9": 990,
      "10": 990,
      "13": 991,
      "14": 991
    },
    "BUS 118": {
      "15": 991,
      "16": 991,
      "17": 991,
      "18": 990,
      "19": 990
    },
    "BUS 207": {
      "12": 991,
      "13": 991,
      "14": 991,
      "16": 991,
      "17": 991
    },
    "BUS 215": {
      "12": 479,
      "13": 479,
      "14": 479,
      "15": 991,
      "16": 991
    },
    "BUS 219": {
      "14": 927,
      "15": 927,
      "16": 478,
      "17": 478
    },
    "Quad 1001": {
      "12": 991,
      "13": 991,
      "14": 991
    },
    "Quad 1042": {
      "8": 8,
      "9": 8,
      "10": 8,
      "11": 8,
      "12": 8,
      "13": 8,
      "14": 10,
      "15": 8,
      "16": 8,
      "17": 8,
      "18": 8
    },
    "Quad 1043": {
      "9": 991,
      "10": 991,
      "11": 842,
      "14": 1023,
      "15": 991,
      "19": 991,
      "20": 991
    },
    "Quad 1045": {
      "15": 15,
      "18": 990,
      "19": 990
    },
    "Quad 1046": {
      "9": 991,
      "10": 991,
      "14": 991,
      "15": 991,
      "16": 991,
      "18": 1023,
      "19": 1023,
      "20": 1023
    },
    "Quad 1047": {
      "11": 95,
      "12": 95,
      "14": 991,
      "15": 991,
      "16": 991,
      "17": 991
    },
    "Quad 1048": {
      "12": 1,
      "13": 15,
      "14": 15,
      "15": 991,
      "16": 991
    },
    "Quad 1049": {
      "8": 8,
      "9": 8,
      "10": 8,
      "11": 8,
      "12": 8,
      "13": 8,
      "14": 8,
      "15": 8,
      "16": 8,
      "17": 8,
      "18": 8
    },
    "Quad G025": {
      "20": 1023,
      "21": 1023
    },
    "Quad G026": {
      "20": 1023,
      "21": 1023
    },
    "Quad G027": {
      "18": 991,
      "19": 991,
      "20": 991
    },
    "Quad G031": {
      "12": 991,
      "13": 991
    },
    "Quad G032": {
      "14": 991,
      "15": 991
    },
    "Quad G033": {
      "8": 12,
      "9": 13,
      "10": 13,
      "11": 13,
      "12": 13,
      "13": 13,
      "14": 13,
      "15": 13,
      "16": 13,
      "17": 13,
      "18": 13,
      "20": 1023,
      "21": 1023
    },
    "Quad G034": {
      "9": 991,
      "10": 991,
      "11": 991,
      "13": 990,
      "14": 991,
      "15": 990,
      "18": 990,
      "19": 990,
      "20": 990
    },
    "Quad G040": {
      "10": 7,
      "11": 7,
      "12": 7,
      "13": 10,
      "14": 2,
      "15": 2,
      "16": 2,
      "17": 2,
      "18": 2,
      "19": 2,
      "20": 1023,
      "21": 1023
    },
    "Quad G042": {
      "15": 1023,
      "20": 1023,
      "21": 1023
    },
    "Quad G044": {
      "9": 991,
      "10": 991,
      "14": 1023,
      "15": 1023,
      "16": 1023,
      "18": 991,
      "19": 991
    },
    "Quad G045": {
      "12": 1023,
      "13": 1023,
      "14": 1023,
      "18": 991,
      "19": 991
    },
    "Quad G046": {
      "9": 2,
      "10": 2,
      "11": 2,
      "12": 2,
      "13": 2,
      "14": 2,
      "15": 2,
      "16": 2,
      "20": 1023,
      "21": 1023
    },
    "Quad G047": {
      "12": 2,
      "13": 2,
      "14": 2,
      "15": 991,
      "16": 991,
      "20": 1023,
      "21": 1023
    },
    "Quad G048": {
      "14": 2,
      "15": 1023,
      "20": 1023,
      "21": 1023
    },
    "Quad G052": {
      "16": 991,
      "17": 991,
      "20": 1023,
      "21": 1023
    },
    "Quad G053": {
      "12": 990,
      "13": 990,
      "15": 991,
      "16": 991,
      "17": 991
    },
    "Quad G054": {
      "8": 8,
      "9": 8,
      "10": 8,
      "11": 8,
      "12": 8,
      "13": 8,
      "14": 8,
      "15": 8,
      "16": 8,
      "17": 8,
      "18": 8,
      "20": 1023,
      "21": 1023
    },
    "Quad G055": {
      "7": 1023,
      "8": 1023,
      "9": 1023,
      "10": 1023,
      "11": 1023,
      "12": 1023,
      "13": 1023,
      "14": 1023,
      "15": 1023,
      "16": 1023,
      "17": 1023,
      "18": 1023,
      "19": 1023,
      "20": 1023,
      "21": 1023
    },
    "Webst 250": {
      "10": 991,
      "11": 991,
      "14": 990,
      "15": 990,
      "16": 990,
      "17": 991
    },
    "Webst 251": {
      "13": 990,
      "14": 990,
      "16": 1023,
      "17": 1023
    },
    "Webst 252": {
      "12": 990,
      "13": 990,
      "14": 990,
      "16": 990,
      "17": 990
    },
    "Webst 256": {
      "10": 63
    },
    "Webst 302": {
      "9": 1023,
      "10": 1023,
      "11": 1023,
      "12": 991,
      "13": 991,
      "14": 991
    },
    "RedC 2035": {
      "11": 478,
      "12": 478,
      "13": 991,
      "14": 991
    },
    "RedC 3037": {
      "10": 991,
      "11": 991,
      "15": 991,
      "16": 991
    },
    "RedC 4034": {
      "11": 991,
      "12": 991,
      "14": 991,
      "15": 991
    },
    "RedC M010": {
      "10": 991,
      "12": 991,
      "13": 991,
      "14": 990,
      "15": 990,
      "16": 990,
      "17": 991
    }
  },
  "wed": {
    "Col LG01": {
      "9": 1023,
      "10": 1023,
      "11": 478,
      "12": 478,
      "13": 991,
      "14": 1023,
      "15": 1023,
      "16": 991,
      "17": 991
    },
    "Col LG02": {
      "9": 1,
      "10": 1,
      "11": 1,
      "12": 1,
      "13": 1,
      "14": 991,
      "15": 991,
      "16": 991,
      "17": 991
    },
    "Gold G01": {
      "11": 1023,
      "12": 1023,
      "13": 991,
      "14": 991,
      "16": 991,
      "17": 991,
      "18": 991
    },
    "Gold G02": {
      "10": 991,
      "11": 991,
      "12": 1022,
      "13": 1022,
      "14": 1022,
      "15": 991,
      "16": 991
    },
    "Gold G03": {
      "12": 991,
      "13": 991,
      "16": 1023,
      "17": 1023
    },
    "Gold G04": {
      "13": 1023,
      "14": 1023,
      "15": 1023
    },
    "Gold G05": {
      "14": 1023,
      "15": 1023
    },
    "Gold G06": {
      "10": 991,
      "11": 991,
      "12": 991,
      "13": 991,
      "14": 991,
      "15": 1022,
      "16": 1022
    },
    "Gold G07": {
      "14": 926,
      "15": 926,
      "16": 926,
      "17": 926
    },
    "Gold G09": {
      "9": 990,
      "12": 991,
      "13": 991,
      "17": 991
    },
    "BUS 107": {
      "10": 991,
      "11": 991,
      "12": 991,
      "13": 991
    },
    "BUS 114": {
      "11": 991,
      "12": 991,
      "13": 991,
      "14": 991,
      "15": 990,
      "16": 990,
      "17": 990,
      "18": 990,
      "19": 990
    },
    "BUS 118": {
      "9": 991,
      "10": 991,
      "11": 991,
      "12": 991,
      "13": 991,
      "14": 926,
      "15": 926,
      "16": 510,
      "17": 510,
      "18": 990,
      "19": 990
    },
    "BUS 207": {
      "9": 991,
      "10": 991,
      "11": 991,
      "12": 991,
      "13": 991,
      "14": 991,
      "15": 991,
      "16": 991
    },
    "BUS 215": {
      "10": 991,
      "11": 991,
      "14": 991,
      "15": 991,
      "16": 991
    },
    "BUS 219": {
      "9": 991,
      "10": 991,
      "11": 991,
      "13": 63,
      "14": 510,
      "15": 510,
      "17": 991,
      "18": 991
    },
    "Quad 1001": {
      "9": 991,
      "10": 991,
      "11": 991,
      "12": 991,
      "13": 991,
      "14": 991
    },
    "Quad 1042": {},
    "Quad 1043": {
      "10": 863,
      "11": 863,
      "12": 863,
      "13": 863,
      "14": 1023,
      "15": 991
    },
    "Quad 1045": {
      "11": 1,
      "12": 1,
      "13": 991,
      "14": 991,
      "15": 990,
      "16": 990
    },
    "Quad 1046": {
      "9": 95,
      "10": 95,
      "11": 95,
      "12": 990,
      "13": 990,
      "14": 990,
      "15": 990,
      "16": 990,
      "17": 990
    },
    "Quad 1047": {
      "13": 991,
      "14": 991,
      "16": 991,
      "17": 991
    },
    "Quad 1048": {
      "13": 15,
      "14": 991,
      "15": 991,
      "17": 15
    },
    "Quad 1049": {
      "15": 510
    },
    "Quad G025": {
      "11": 1023,
      "12": 1023,
      "13": 63,
      "14": 991,
      "15": 991,
      "16": 478,
      "17": 478
    },
    "Quad G026": {
      "9": 64,
      "10": 64,
      "11": 991,
      "12": 991,
      "13": 927,
      "14": 64,
      "15": 65,
      "16": 65
    },
    "Quad G027": {
      "11": 1,
      "12": 1,
      "13": 1,
      "14": 1,
      "15": 1
    },
    "Quad G031": {
      "11": 991,
      "12": 991,
      "13": 1023,
      "14": 1023,
      "15": 991,
      "16": 991,
      "17": 991
    },
    "Quad G032": {
      "9": 991,
      "10": 991,
      "11": 991,
      "12": 991,
      "13": 991,
      "14": 991
    },
    "Quad G033": {
      "8": 12,
      "9": 13,
      "10": 13,
      "11": 13,
      "12": 13,
      "13": 13,
      "14": 13,
      "15": 13,
      "16": 13,
      "17": 13,
      "18": 13
    },
    "Quad G034": {
      "11": 1,
      "12": 3,
      "13": 3,
      "14": 3,
      "15": 1,
      "16": 1,
      "17": 1023,
      "18": 1023,
      "19": 1
    },
    "Quad G040": {
      "9": 991,
      "10": 991,
      "11": 991,
      "12": 991,
      "13": 991,
      "14": 991,
      "16": 990,
      "17": 990,
      "18": 990,
      "19": 990
    },
    "Quad G042": {},
    "Quad G044": {
      "12": 1023,
      "13": 1023,
      "15": 1023,
      "16": 1023
    },
    "Quad G045": {
      "12": 990,
      "13": 990,
      "14": 990,
      "15": 990,
      "16": 990,
      "17": 990
    },
    "Quad G046": {
      "9": 926,
      "10": 926,
      "11": 926,
      "12": 926,
      "14": 991,
      "15": 991
    },
    "Quad G047": {
      "9": 1022,
      "10": 1023,
      "11": 991,
      "13": 991,
      "14": 991,
      "15": 991,
      "16": 991,
      "17": 991
    },
    "Quad G048": {
      "9": 2,
      "10": 2,
      "11": 2,
      "12": 2,
      "13": 2,
      "14": 2,
      "15": 2,
      "16": 2
    },
    "Quad G052": {
      "10": 1023,
      "11": 1023,
      "12": 1023,
      "13": 1023,
      "18": 991,
      "19": 991
    },
    "Quad G053": {
      "9": 991,
      "10": 991,
      "11": 991,
      "12": 1023,
      "13": 1023,
      "14": 1023,
      "16": 990
    },
    "Quad G054": {},
    "Quad G055": {
      "7": 1023,
      "8": 1023,
      "9": 1023,
      "10": 1023,
      "11": 1023,
      "12": 1023,
      "13": 1023,
      "14": 1023,
      "15": 1023,
      "16": 1023,
      "17": 1023,
      "18": 1023,
      "19": 1023,
      "20": 1023,
      "21": 1023
    },
    "Webst 250": {
      "9": 991,
      "10": 991,
      "11": 991,
      "12": 991,
      "13": 991,
      "14": 991,
      "15": 991,
      "16": 991,
      "17": 991,
      "18": 991
    },
    "Webst 251": {
      "10": 911,
      "11": 911,
      "12": 991,
      "13": 991,
      "19": 991,
      "20": 991
    },
    "Webst 252": {
      "13": 990,
      "14": 990,
      "16": 990,
      "17": 990,
      "18": 991,
      "19": 991,
      "20": 990
    },
    "Webst 256": {
      "9": 991,
      "10": 991,
      "13": 991,
      "14": 991,
      "17": 991,
      "18": 991
    },
    "Webst 302": {
      "9": 991,
      "10": 991,
      "11": 991,
      "12": 991,
      "13": 990,
      "14": 990,
      "15": 991,
      "16": 991
    },
    "RedC 2035": {
      "11": 991,
      "12": 991
    },
    "RedC 3037": {
      "9": 991,
      "10": 991,
      "14": 991,
      "15": 991,
      "16": 991,
      "17": 991
    },
    "RedC 4034": {
      "15": 666,
      "16": 666
    },
    "RedC M010": {
      "11": 990,
      "12": 990,
      "13": 990
    }
  },
  "thu": {
    "Col LG01": {
      "9": 991,
      "10": 991,
      "11": 991,
      "12": 991,
      "13": 478,
      "14": 478,
      "15": 1023,
      "16": 1023
    },
    "Col LG02": {
      "10": 991,
      "12": 991,
      "13": 991,
      "14": 991,
      "15": 991,
      "16": 1023,
      "17": 2,
      "18": 2
    },
    "Gold G01": {
      "10": 478,
      "11": 478,
      "12": 991,
      "13": 991,
      "14": 991,
      "15": 1023,
      "16": 1023,
      "18": 991,
      "19": 991
    },
    "Gold G02": {
      "12": 991,
      "13": 991,
      "14": 991,
      "15": 1023,
      "16": 1023
    },
    "Gold G03": {
      "12": 991,
      "13": 991,
      "14": 991,
      "15": 1023,
      "16": 1023
    },
    "Gold G04": {
      "9": 2,
      "10": 2,
      "11": 2,
      "12": 2,
      "13": 2,
      "14": 2,
      "15": 2,
      "16": 2,
      "17": 1023,
      "18": 1023
    },
    "Gold G05": {
      "14": 926,
      "15": 926,
      "16": 926,
      "17": 926
    },
    "Gold G06": {
      "12": 990,
      "13": 990,
      "15": 1023,
      "16": 1023,
      "18": 926,
      "19": 926
    },
    "Gold G07": {
      "15": 1023,
      "16": 1023
    },
    "Gold G09": {
      "9": 527,
      "10": 527,
      "11": 991,
      "12": 991,
      "14": 1023,
      "15": 1023,
      "16": 990,
      "17": 990,
      "18": 990,
      "19": 990
    },
    "BUS 107": {
      "9": 926,
      "10": 926,
      "11": 2,
      "12": 2,
      "13": 2,
      "14": 2,
      "15": 2,
      "18": 991
    },
    "BUS 114": {
      "10": 991,
      "11": 991,
      "13": 990,
      "14": 990,
      "15": 990,
      "16": 990
    },
    "BUS 118": {
      "9": 991,
      "10": 991,
      "11": 991,
      "14": 991,
      "15": 990,
      "16": 990
    },
    "BUS 207": {
      "9": 991,
      "10": 991,
      "11": 926,
      "12": 926,
      "16": 990,
      "17": 990
    },
    "BUS 215": {
      "9": 991,
      "10": 991,
      "11": 991,
      "12": 991,
      "13": 991,
      "14": 991,
      "15": 1023,
      "16": 1023
    },
    "BUS 219": {
      "14": 63,
      "15": 991,
      "16": 991,
      "17": 991,
      "19": 991,
      "20": 991
    },
    "Quad 1001": {
      "10": 478,
      "11": 478,
      "12": 478,
      "13": 478,
      "15": 1023,
      "16": 1023
    },
    "Quad 1042": {
      "9": 2,
      "10": 2,
      "11": 2,
      "12": 2,
      "13": 2,
      "14": 2,
      "15": 2,
      "16": 1023,
      "17": 1023,
      "18": 1023
    },
    "Quad 1043": {
      "10": 256,
      "11": 256,
      "13": 2,
      "14": 2,
      "16": 991,
      "17": 991,
      "19": 1023,
      "20": 1023
    },
    "Quad 1045": {
      "9": 991,
      "10": 991,
      "11": 991,
      "16": 991
    },
    "Quad 1046": {
      "9": 990,
      "10": 990,
      "12": 991,
      "13": 991,
      "15": 1023,
      "16": 1023
    },
    "Quad 1047": {
      "9": 990,
      "10": 990,
      "12": 990,
      "13": 990,
      "14": 990
    },
    "Quad 1048": {
      "9": 1022,
      "10": 1022,
      "11": 1022,
      "12": 991,
      "13": 991,
      "15": 990,
      "16": 990,
      "17": 990
    },
    "Quad 1049": {
      "10": 991,
      "11": 991,
      "15": 1023,
      "16": 1023
    },
    "Quad G025": {
      "9": 991,
      "10": 991,
      "11": 991,
      "15": 991,
      "16": 991,
      "17": 991
    },
    "Quad G026": {
      "9": 991,
      "10": 991,
      "11": 991,
      "15": 1023,
      "16": 1023
    },
    "Quad G027": {
      "10": 991,
      "11": 991,
      "12": 478,
      "13": 478,
      "15": 1023,
      "16": 1023
    },
    "Quad G031": {
      "12": 991,
      "13": 991,
      "14": 991,
      "15": 991,
      "16": 991
    },
    "Quad G032": {
      "10": 991,
      "11": 991,
      "12": 991,
      "13": 991,
      "14": 991
    },
    "Quad G033": {
      "8": 12,
      "9": 13,
      "10": 13,
      "11": 13,
      "12": 13,
      "13": 13,
      "14": 13,
      "15": 13,
      "16": 13,
      "17": 13,
      "18": 13
    },
    "Quad G034": {
      "9": 991,
      "10": 991,
      "13": 991,
      "14": 990,
      "15": 1023,
      "16": 1023,
      "17": 1023,
      "18": 1023,
      "19": 1023,
      "20": 1023
    },
    "Quad G040": {
      "9": 991,
      "10": 991,
      "12": 991,
      "13": 991,
      "14": 991,
      "15": 1023,
      "16": 1023,
      "17": 991,
      "18": 991
    },
    "Quad G042": {
      "10": 991,
      "11": 991,
      "13": 1023,
      "15": 1023,
      "16": 1023
    },
    "Quad G044": {
      "15": 990,
      "16": 1023,
      "17": 1023
    },
    "Quad G045": {
      "9": 990,
      "10": 990,
      "11": 990,
      "12": 990,
      "13": 990,
      "14": 990
    },
    "Quad G046": {
      "12": 991,
      "13": 991,
      "14": 991
    },
    "Quad G047": {
      "10": 1022,
      "11": 1022,
      "12": 991,
      "13": 991,
      "15": 1022,
      "16": 1022,
      "17": 1022
    },
    "Quad G048": {
      "10": 991,
      "11": 991,
      "13": 1023,
      "15": 1023,
      "16": 1023,
      "17": 1022,
      "18": 1022
    },
    "Quad G052": {
      "9": 2,
      "10": 2,
      "11": 2,
      "12": 2,
      "13": 2,
      "15": 1023,
      "16": 1023
    },
    "Quad G053": {
      "9": 1023,
      "10": 1023,
      "11": 1023,
      "13": 991,
      "14": 991,
      "15": 991,
      "16": 991,
      "17": 991,
      "18": 991
    },
    "Quad G054": {
      "9": 2,
      "10": 2,
      "11": 2,
      "12": 2,
      "13": 2,
      "14": 2,
      "15": 2,
      "16": 2
    },
    "Quad G055": {
      "7": 1023,
      "8": 1023,
      "9": 1023,
      "10": 1023,
      "11": 1023,
      "12": 1023,
      "13": 1023,
      "14": 1023,
      "15": 1023,
      "16": 1023,
      "17": 1023,
      "18": 1023,
      "19": 1023,
      "20": 1023,
      "21": 1023
    },
    "Webst 250": {
      "10": 990,
      "11": 990,
      "12": 990,
      "13": 990,
      "15": 1023,
      "16": 1023
    },
    "Webst 251": {
      "9": 1023,
      "10": 1023,
      "11": 1023,
      "12": 1023,
      "13": 1023,
      "14": 1023,
      "15": 1023,
      "16": 1023
    },
    "Webst 252": {
      "12": 990,
      "13": 990,
      "14": 990,
      "15": 1023,
      "16": 1023
    },
    "Webst 256": {
      "11": 991,
      "12": 991,
      "13": 991,
      "14": 991,
      "15": 991,
      "16": 991
    },
    "Webst 302": {
      "11": 991,
      "12": 991,
      "13": 991,
      "14": 991,
      "15": 1023,
      "16": 1023
    },
    "RedC 2035": {
      "12": 990,
      "13": 990,
      "15": 1023,
      "16": 1023
    },
    "RedC 3037": {
      "15": 1023,
      "16": 1023
    },
    "RedC 4034": {
      "10": 991,
      "11": 991,
      "12": 926,
      "13": 926,
      "15": 1023,
      "16": 1023
    },
    "RedC M010": {
      "9": 991,
      "10": 991,
      "11": 991,
      "15": 1023,
      "16": 1023
    }
  },
  "fri": {
    "Col LG01": {
      "11": 913,
      "12": 913,
      "13": 32,
      "14": 959,
      "15": 959,
      "17": 1023,
      "18": 1023,
      "19": 1
    },
    "Col LG02": {
      "10": 927,
      "12": 959,
      "13": 959,
      "14": 927,
      "15": 927,
      "16": 927,
      "17": 1022,
      "18": 1022,
      "19": 2,
      "20": 2
    },
    "Gold G01": {
      "10": 2,
      "11": 2,
      "12": 2,
      "13": 2,
      "14": 2,
      "15": 2,
      "16": 2,
      "17": 2
    },
    "Gold G02": {
      "9": 927,
      "10": 927,
      "11": 927,
      "12": 927,
      "13": 927,
      "14": 926,
      "15": 926
    },
    "Gold G03": {
      "9": 1,
      "10": 1,
      "11": 1,
      "12": 1,
      "13": 5,
      "14": 4,
      "15": 4,
      "16": 1023,
      "17": 1023,
      "18": 1023,
      "19": 1023
    },
    "Gold G04": {
      "14": 511,
      "15": 511,
      "16": 511
    },
    "Gold G05": {
      "14": 927,
      "15": 927
    },
    "Gold G06": {
      "15": 1023,
      "16": 1023,
      "17": 1023
    },
    "Gold G07": {
      "11": 927,
      "12": 927,
      "13": 927,
      "14": 927,
      "15": 927
    },
    "Gold G09": {
      "10": 1,
      "11": 1,
      "12": 5,
      "13": 5,
      "14": 4,
      "15": 927,
      "16": 927
    },
    "BUS 107": {
      "10": 927,
      "11": 927,
      "12": 927,
      "13": 927,
      "16": 926,
      "17": 926
    },
    "BUS 114": {
      "9": 927,
      "10": 927,
      "11": 927,
      "13": 927,
      "14": 927
    },
    "BUS 118": {
      "10": 927,
      "11": 927,
      "12": 926,
      "13": 926
    },
    "BUS 207": {
      "11": 927,
      "12": 927,
      "13": 927,
      "15": 927,
      "16": 927,
      "17": 927
    },
    "BUS 215": {
      "9": 927,
      "10": 927,
      "11": 927,
      "12": 927,
      "13": 927,
      "15": 927,
      "16": 927,
      "17": 927
    },
    "BUS 219": {
      "9": 927,
      "10": 927,
      "11": 927,
      "12": 927,
      "13": 927,
      "15": 927,
      "16": 927,
      "17": 927
    },
    "Quad 1001": {
      "14": 266,
      "15": 266
    },
    "Quad 1042": {},
    "Quad 1043": {
      "9": 527,
      "10": 527,
      "11": 527,
      "12": 527,
      "13": 927,
      "14": 959,
      "15": 959,
      "16": 927,
      "17": 927
    },
    "Quad 1045": {
      "9": 4,
      "10": 4,
      "11": 4,
      "12": 4,
      "13": 4,
      "14": 4,
      "15": 4,
      "16": 4
    },
    "Quad 1046": {
      "9": 927,
      "10": 927,
      "13": 2
    },
    "Quad 1047": {
      "11": 927,
      "12": 927,
      "15": 927,
      "16": 927
    },
    "Quad 1048": {
      "11": 15,
      "13": 15,
      "14": 15
    },
    "Quad 1049": {},
    "Quad G025": {
      "11": 1023,
      "12": 1023,
      "13": 63,
      "14": 24,
      "15": 24,
      "16": 24,
      "17": 24
    },
    "Quad G026": {
      "11": 1022,
      "12": 1022,
      "17": 1023,
      "18": 1023,
      "19": 1023,
      "20": 1023,
      "21": 1023
    },
    "Quad G027": {
      "11": 927,
      "12": 927,
      "13": 927,
      "14": 927
    },
    "Quad G031": {
      "9": 958,
      "10": 958,
      "11": 958,
      "17": 1023,
      "18": 1023,
      "19": 1023,
      "20": 1023,
      "21": 1023
    },
    "Quad G032": {
      "17": 1023,
      "18": 1023,
      "19": 1023,
      "20": 1023,
      "21": 1023
    },
    "Quad G033": {
      "8": 12,
      "9": 13,
      "10": 13,
      "11": 13,
      "12": 13,
      "13": 13,
      "14": 13,
      "15": 13,
      "16": 13,
      "17": 13,
      "18": 13
    },
    "Quad G034": {
      "9": 927,
      "11": 927,
      "12": 63,
      "13": 959,
      "14": 24,
      "15": 927,
      "16": 959,
      "17": 959,
      "18": 2,
      "19": 2,
      "20": 2
    },
    "Quad G040": {
      "11": 661,
      "12": 661,
      "15": 927,
      "16": 927
    },
    "Quad G042": {},
    "Quad G044": {
      "11": 927,
      "12": 927,
      "13": 927,
      "14": 927
    },
    "Quad G045": {},
    "Quad G046": {},
    "Quad G047": {},
    "Quad G048": {
      "9": 2,
      "10": 2,
      "11": 2,
      "12": 2,
      "13": 2,
      "14": 2,
      "15": 2,
      "16": 2
    },
    "Quad G052": {},
    "Quad G053": {
      "9": 927,
      "10": 927,
      "11": 927,
      "12": 927,
      "13": 927,
      "14": 927,
      "18": 2,
      "19": 2,
      "20": 2
    },
    "Quad G054": {
      "11": 926,
      "12": 926
    },
    "Quad G055": {
      "7": 1023,
      "8": 1023,
      "9": 1023,
      "10": 1023,
      "11": 1023,
      "12": 1023,
      "13": 1023,
      "14": 1023,
      "15": 1023,
      "16": 1023,
      "17": 1023,
      "18": 1023,
      "19": 1023,
      "20": 1023,
      "21": 1023
    },
    "Webst 250": {
      "9": 927,
      "10": 927,
      "11": 927,
      "12": 927,
      "14": 927,
      "15": 927,
      "16": 927
    },
    "Webst 251": {
      "9": 927,
      "10": 927,
      "11": 927,
      "12": 927,
      "13": 2,
      "14": 2,
      "15": 2,
      "16": 927,
      "17": 927
    },
    "Webst 252": {
      "9": 926,
      "10": 926,
      "11": 926,
      "12": 926,
      "14": 926,
      "15": 926,
      "16": 926,
      "17": 926
    },
    "Webst 256": {
      "14": 63
    },
    "Webst 302": {
      "11": 927,
      "12": 927
    },
    "RedC 2035": {
      "9": 1,
      "10": 1,
      "11": 1,
      "12": 1,
      "13": 927,
      "14": 927
    },
    "RedC 3037": {
      "12": 926,
      "13": 926,
      "15": 927,
      "16": 927
    },
    "RedC 4034": {},
    "RedC M010": {
      "11": 521,
      "12": 521
    }
  },
  "sat": {
    "Col LG01": {
      "12": 1023,
      "13": 1023,
      "14": 1023,
      "15": 1023,
      "16": 1023,
      "17": 1023,
      "18": 1023,
      "19": 1023
    },
    "Col LG02": {
      "12": 1023,
      "13": 1023,
      "14": 1023,
      "15": 1023,
      "16": 1023,
      "17": 1023,
      "18": 1023,
      "19": 1023
    },
    "Gold G01": {
      "8": 16,
      "9": 16,
      "10": 16,
      "11": 16,
      "12": 16,
      "13": 16,
      "14": 16,
      "15": 16,
      "16": 16
    },
    "Gold G02": {
      "8": 16,
      "9": 16,
      "10": 16,
      "11": 16,
      "12": 16,
      "13": 16,
      "14": 16,
      "15": 16,
      "16": 16
    },
    "Gold G03": {},
    "Gold G04": {},
    "Gold G05": {
      "8": 16,
      "9": 16,
      "10": 16,
      "11": 16,
      "12": 16,
      "13": 16,
      "14": 16,
      "15": 16,
      "16": 16
    },
    "Gold G06": {},
    "Gold G07": {},
    "Gold G09": {},
    "BUS 107": {},
    "BUS 114": {},
    "BUS 118": {},
    "BUS 207": {},
    "BUS 215": {},
    "BUS 219": {},
    "Quad 1001": {},
    "Quad 1042": {},
    "Quad 1043": {
      "11": 1,
      "12": 1
    },
    "Quad 1045": {},
    "Quad 1046": {},
    "Quad 1047": {},
    "Quad 1048": {},
    "Quad 1049": {},
    "Quad G025": {
      "8": 2,
      "9": 2,
      "10": 2,
      "11": 2,
      "12": 2,
      "13": 2,
      "14": 2,
      "15": 2
    },
    "Quad G026": {},
    "Quad G027": {
      "9": 2,
      "10": 2,
      "11": 2,
      "12": 2,
      "13": 2,
      "14": 2,
      "15": 2,
      "16": 2
    },
    "Quad G031": {
      "8": 2,
      "9": 2,
      "10": 2,
      "11": 2,
      "12": 2,
      "13": 2,
      "14": 2,
      "15": 2
    },
    "Quad G032": {},
    "Quad G033": {},
    "Quad G034": {
      "14": 2,
      "15": 2,
      "16": 2,
      "17": 2
    },
    "Quad G040": {},
    "Quad G042": {},
    "Quad G044": {},
    "Quad G045": {},
    "Quad G046": {},
    "Quad G047": {},
    "Quad G048": {},
    "Quad G052": {},
    "Quad G053": {},
    "Quad G054": {},
    "Quad G055": {
      "7": 1023,
      "8": 1023,
      "9": 1023,
      "10": 1023,
      "11": 1023,
      "12": 1023,
      "13": 1023,
      "14": 1023,
      "15": 1023,
      "16": 1023,
      "17": 1023,
      "18": 1023,
      "19": 1023,
      "20": 1023,
      "21": 1023
    },
    "Webst 250": {},
    "Webst 251": {},
    "Webst 252": {},
    "Webst 256": {},
    "Webst 302": {},
    "RedC 2035": {},
    "RedC 3037": {},
    "RedC 4034": {},
    "RedC M010": {}
  },
  "sun": {
    "Col LG01": {
      "12": 2,
      "13": 2,
      "14": 2,
      "15": 2,
      "16": 2,
      "17": 2,
      "18": 2
    },
    "Col LG02": {
      "12": 2,
      "13": 2,
      "14": 2,
      "15": 2,
      "16": 2,
      "17": 2,
      "18": 2
    },
    "Gold G01": {
      "8": 16,
      "9": 16,
      "10": 16,
      "11": 16,
      "12": 16,
      "13": 16,
      "14": 16,
      "15": 16,
      "16": 16
    },
    "Gold G02": {
      "8": 16,
      "9": 16,
      "10": 16,
      "11": 16,
      "12": 16,
      "13": 16,
      "14": 16,
      "15": 16,
      "16": 16
    },
    "Gold G03": {},
    "Gold G04": {},
    "Gold G05": {
      "8": 16,
      "9": 16,
      "10": 16,
      "11": 16,
      "12": 16,
      "13": 16,
      "14": 16,
      "15": 16,
      "16": 16
    },
    "Gold G06": {
      "8": 2,
      "9": 2,
      "10": 2,
      "11": 2,
      "12": 2,
      "13": 2,
      "14": 2,
      "15": 2,
      "16": 2,
      "17": 2,
      "18": 2,
      "19": 2
    },
    "Gold G07": {
      "8": 2,
      "9": 2,
      "10": 2,
      "11": 2,
      "12": 2,
      "13": 2,
      "14": 2,
      "15": 2,
      "16": 2,
      "17": 2,
      "18": 2,
      "19": 2
    },
    "Gold G09": {
      "8": 2,
      "9": 2,
      "10": 2,
      "11": 2,
      "12": 2,
      "13": 2,
      "14": 2,
      "15": 2,
      "16": 2,
      "17": 2,
      "18": 2,
      "19": 2
    },
    "BUS 107": {},
    "BUS 114": {},
    "BUS 118": {},
    "BUS 207": {},
    "BUS 215": {},
    "BUS 219": {},
    "Quad 1001": {},
    "Quad 1042": {},
    "Quad 1043": {},
    "Quad 1045": {},
    "Quad 1046": {},
    "Quad 1047": {},
    "Quad 1048": {},
    "Quad 1049": {},
    "Quad G025": {},
    "Quad G026": {},
    "Quad G027": {
      "9": 2,
      "10": 2,
      "11": 2,
      "12": 2,
      "13": 2,
      "14": 2,
      "15": 2,
      "16": 2
    },
    "Quad G031": {},
    "Quad G032": {},
    "Quad G033": {},
    "Quad G034": {
      "16": 2,
      "17": 2
    },
    "Quad G040": {},
    "Quad G042": {},
    "Quad G044": {},
    "Quad G045": {},
    "Quad G046": {},
    "Quad G047": {},
    "Quad G048": {},
    "Quad G052": {},
    "Quad G053": {},
    "Quad G054": {},
    "Quad G055": {
      "7": 1023,
      "8": 1023,
      "9": 1023,
      "10": 1023,
      "11": 1023,
      "12": 1023,
      "13": 1023,
      "14": 1023,
      "15": 1023,
      "16": 1023,
      "17": 1023,
      "18": 1023,
      "19": 1023,
      "20": 1023,
      "21": 1023
    },
    "Webst 250": {},
    "Webst 251": {},
    "Webst 252": {},
    "Webst 256": {},
    "Webst 302": {},
    "RedC 2035": {},
    "RedC 3037": {},
    "RedC 4034": {},
    "RedC M010": {}
  }
}